{"name":"Hubert Hurkacz","country":"POL","current":68,"age":29,"height":196,"weight":81,"hand":"Right-Handed","history":{"official":[{"date":"2025-01-01","rank":16},{"date":"2025-02-01","rank":21},{"date":"2025-03-01","rank":20},{"date":"2025-04-01","rank":22},{"date":"2025-05-01","rank":28},{"date":"2025-06-01","rank":28},{"date":"2025-07-01","rank":39},{"date":"2025-08-01","rank":37},{"date":"2025-09-01","rank":68},{"date":"2025-10-01","rank":78},{"date":"2025-11-01","rank":77},{"date":"2025-12-01","rank":73},{"date":"2026-01-01","rank":72},{"date":"2026-02-01","rank":55},{"date":"2026-03-01","rank":73},{"date":"2026-04-01","rank":72},{"date":"2026-05-01","rank":63},{"date":"2026-06-01","rank":99},{"date":"2026-07-01","rank":96},{"date":"2026-07-15","rank":68}]}}